README.md
setup.py
aws/__init__.py
az/__init__.py
cloud_toolkit.egg-info/PKG-INFO
cloud_toolkit.egg-info/SOURCES.txt
cloud_toolkit.egg-info/dependency_links.txt
cloud_toolkit.egg-info/requires.txt
cloud_toolkit.egg-info/top_level.txt
remote/__init__.py