Metadata-Version: 2.1
Name: cloud-toolkit
Version: 1.0.9
Summary: A toolkit help to management cloud iot.
Home-page: https://github.com/GaryHsu77/cloud-iot-toolkit
Author: garyhsu
Author-email: bibbylong@hotmail.com
License: MIT License
Keywords: cloud,iot,azure,aws
Platform: any
Classifier: Development Status :: 3 - Alpha
Classifier: Intended Audience :: Developers
Classifier: Topic :: Software Development :: Build Tools
Classifier: License :: OSI Approved :: MIT License
Classifier: Programming Language :: Python :: 3.7
Requires-Python: >=3.6
